Comfort1.v
`timescale 1ns / 1ps
module Comfort1
(
input clk,reset,motion_sen,
input [5:0]temp_sen,lume_sen,
output reg heater,cooler,light_high
);
reg [2:0]current_state,next_state;
parameter A=3'b000,B=3'b001,C=3'b010,D=3'b011,E=3'b100;
always@(posedge clk or posedge reset or negedge motion_sen) begin
if(reset) current_state<=A;
else if(!motion_sen) current_state<=0;
else current_state<=next_state;
end
always@(posedge clk,current_state,motion_sen,reset,temp_sen,lume_sen) begin
case(current_state)
A:begin
if(temp_sen<15&&lume_sen<15)begin
next_state<=B;
heater=1'b1;
cooler=1'b0;
light_high=1'b1;
end
else if(temp_sen<15&&lume_sen>15)begin
next_state<=C;
heater=1'b1;
cooler=1'b0;
light_high=1'b0;end
else if(temp_sen>30&&lume_sen<15)begin
next_state<=D;
heater=1'b0;
cooler=1'b1;
light_high=1'b1;
end
else if(temp_sen>30&&lume_sen>15)begin
next_state<=E;
heater=1'b0;
cooler=1'b1;
light_high=1'b0;
end
else begin next_state<=A;
heater=1'b0;
cooler=1'b0;
light_high=1'b0;
end
end
B:begin
if(temp_sen<15&&lume_sen>15)begin
next_state<=C;
heater=1'b1;
cooler=1'b0;
light_high=1'b0;
end
else if(temp_sen>30&&lume_sen<15)begin
next_state<=D;
heater=1'b0;
cooler=1'b1;
light_high=1'b1;
end
else if(temp_sen>30&&lume_sen>15)begin
next_state<=E;
heater=1'b0;
cooler=1'b1;
light_high=1'b0;
end
else begin
next_state<=B;
heater=1'b1;
cooler=1'b0;
light_high=1'b1;
end
end
C:begin
if(temp_sen<15&&lume_sen<15)begin
next_state<=B;
heater=1'b1;
cooler=1'b0;
light_high=1'b1;
end
else if(temp_sen>30&&lume_sen<15)begin
next_state<=D;
heater=1'b0;
cooler=1'b1;light_high=1'b1;
end
else if(temp_sen>30&&lume_sen>15)begin
next_state<=E;
heater=1'b0;
cooler=1'b1;
light_high=1'b0;
end
else begin
next_state<=C;
heater=1'b1;
cooler=1'b0;
light_high=1'b0;
end
end
D:begin
if(temp_sen<15&&lume_sen<15)begin
next_state<=B;
heater=1'b1;
cooler=1'b0;
light_high=1'b1;
end
else if(temp_sen<15&&lume_sen>15)begin
next_state<=C;
heater=1'b1;
cooler=1'b0;
light_high=1'b0;
end
else if(temp_sen>30&&lume_sen>15)begin
next_state<=E;
heater=1'b0;
cooler=1'b1;
light_high=1'b0;
end
else begin
next_state<=D;
heater=1'b0;
cooler=1'b1;
light_high=1'b1;
end
end
E:begin
if(temp_sen<15&&lume_sen<15)begin
next_state<=B;
heater=1'b1;
cooler=1'b0;
light_high=1'b1;
end
else if(temp_sen<15&&lume_sen>15)begin
next_state<=C;
heater=1'b1;
cooler=1'b0;light_high=1'b0;
end
else if(temp_sen>30&&lume_sen<15)begin
next_state<=D;
heater=1'b0;
cooler=1'b1;
light_high=1'b1;
end
else begin
next_state<=E;
heater=1'b0;
cooler=1'b1;
light_high=1'b0;
end
end
default: next_state<=A;
endcase
end
endmodule

comfort_tb.v
`timescale 1ns / 1ps
module comfort_tb();
  reg clk, reset, motion_sen;
  reg [5:0] temp_sen, lume_sen;
  wire heater, cooler, light_high;
  
  Comfort1 vi(
    .clk(clk),
    .reset(reset),
    .motion_sen(motion_sen),
    .temp_sen(temp_sen),
    .lume_sen(lume_sen),
    .heater(heater),
    .cooler(cooler),
    .light_high(light_high)
  );

  initial begin
    $dumpfile("dump.vcd"); 
    $dumpvars(0, comfort_tb);
    clk = 1;
    forever #5 clk = ~clk;
  end
  
  initial begin
    reset = 1;
    #10;
    reset = 0;
    motion_sen = 1;
    temp_sen = 35;
    lume_sen = 17;
    #10;
    reset = 0;
    motion_sen = 1;
    temp_sen = 14;
    lume_sen = 17;
    #10;
    reset = 0;
    motion_sen = 1;
    temp_sen = 31;
    lume_sen = 11;
    #10;
    reset = 0;
    motion_sen = 1;
    temp_sen = 32;
    lume_sen = 16;
    #10;
    reset = 0;
    motion_sen = 1;
    temp_sen = 21;
    lume_sen = 16;
    #10;
    reset = 0;
    motion_sen = 0;
    temp_sen = 21;
    lume_sen = 14;
    #10;
    reset = 0;
    motion_sen = 1;
    temp_sen = 13;
    lume_sen = 12;
    #10;
    reset = 0;
    motion_sen = 1;
    temp_sen = 35;
    lume_sen = 9;
    #10;
    reset = 0;
    motion_sen = 1;
    temp_sen = 26;
    lume_sen = 9;
    #10;
    $finish;
  end
endmodule

dump.vcd
$date
	Wed Apr 17 16:25:04 2024
$end
$version
	Icarus Verilog
$end
$timescale
	1ps
$end
$scope module comfort_tb $end
$var wire 1 ! light_high $end
$var wire 1 " heater $end
$var wire 1 # cooler $end
$var reg 1 $ clk $end
$var reg 6 % lume_sen [5:0] $end
$var reg 1 & motion_sen $end
$var reg 1 ' reset $end
$var reg 6 ( temp_sen [5:0] $end
$scope module vi $end
$var wire 1 $ clk $end
$var wire 6 ) lume_sen [5:0] $end
$var wire 1 & motion_sen $end
$var wire 1 ' reset $end
$var wire 6 * temp_sen [5:0] $end
$var parameter 3 + A $end
$var parameter 3 , B $end
$var parameter 3 - C $end
$var parameter 3 . D $end
$var parameter 3 / E $end
$var reg 1 # cooler $end
$var reg 3 0 current_state [2:0] $end
$var reg 1 " heater $end
$var reg 1 ! light_high $end
$var reg 3 1 next_state [2:0] $end
$upscope $end
$upscope $end
$enddefinitions $end
$comment Show the parameter values. $end
$dumpall
b100 /
b11 .
b10 -
b1 ,
b0 +
$end
#0
$dumpvars
b0 1
b0 0
bx *
bx )
bx (
1'
x&
bx %
1$
0#
0"
0!
$end
#5000
0$
#10000
b100 1
1#
1$
b10001 %
b10001 )
b100011 (
b100011 *
1&
0'
#15000
0$
#20000
b100 0
b10 1
0#
1"
1$
b1110 (
b1110 *
#25000
0$
#30000
b10 0
b11 1
1!
1#
0"
1$
b1011 %
b1011 )
b11111 (
b11111 *
#35000
0$
#40000
b11 0
b100 1
0!
1$
b10000 %
b10000 )
b100000 (
b100000 *
#45000
0$
#50000
b100 0
b100 1
0!
1$
b10101 (
b10101 *
#55000
0$
#60000
b0 1
0#
b0 0
1$
b1110 %
b1110 )
0&
#65000
0$
#70000
b1 1
1!
1"
1$
b1100 %
b1100 )
b1101 (
b1101 *
1&
#75000
0$
#80000
b1 0
b11 1
1#
0"
1$
b1001 %
b1001 )
b100011 (
b100011 *
#85000
0$
#90000
b11 0
b11 1
1#
0"
1$
b11010 (
b11010 *
